ani_sched/__init__.py
ani_sched/_ani_sched.py
ani_sched/_base.py
ani_sched/_news.py
ani_sched/_recently_aired.py
ani_sched/config.py
ani_sched1-0.1.1.dist-info/LICENSE
ani_sched1-0.1.1.dist-info/METADATA
ani_sched1-0.1.1.dist-info/WHEEL
ani_sched1-0.1.1.dist-info/top_level.txt
ani_sched1-0.1.1.dist-info/RECORD
